README.rst
setup.cfg
setup.py
smuggle/__init__.py
smuggle/core.py
smuggle.egg-info/PKG-INFO
smuggle.egg-info/SOURCES.txt
smuggle.egg-info/dependency_links.txt
smuggle.egg-info/top_level.txt