Metadata-Version: 1.1
Name: smuggle
Version: 0.1rc2
Summary: Log, catalogue, and move python objects via pickling
Home-page: https://github.com/jnmclarty/smuggle
Author: Jeffrey McLarty
Author-email: jeffrey.mclarty@gmail.com
License: UNKNOWN
Download-URL: https://github.com/jnmclarty/smuggle/tarball/0.1rc2
Keywords: debugging,logging,smuggle,smuggler,exception,pickle,pickling
Platform: UNKNOWN
Classifier: Development Status :: 4 - Beta
Classifier: Topic :: Office/Business
Classifier: Operating System :: OS Independent
Classifier: Programming Language :: Python :: 2.7
Classifier: Topic :: Software Development
Classifier: Topic :: System :: Logging
Classifier: Topic :: Utilities
